stdocker/__init__.py
stdocker/cli.py
stdocker/config.py
stdocker/env_handler.py
stdocker/env_parser.py
stdocker/utils.py
stdocker/version.py
stdocker/yaml_parser.py
stdocker-1.2.8.dist-info/LICENSE
stdocker-1.2.8.dist-info/METADATA
stdocker-1.2.8.dist-info/WHEEL
stdocker-1.2.8.dist-info/entry_points.txt
stdocker-1.2.8.dist-info/top_level.txt
stdocker-1.2.8.dist-info/RECORD
