Metadata-Version: 2.1
Name: stdocker
Version: 1.2.8
Summary: Shinetech Docker CLI.
Home-page: https://github.com/winds1983/stdocker
Author: Jason Sun
Author-email: sunf@shinetechsoftware.com
License: MIT
Keywords: python package,stdocker,shinetech,docker,development environment
Platform: UNKNOWN
Classifier: Programming Language :: Python
Classifier: Programming Language :: Python :: 3
Classifier: Programming Language :: Python :: 3.8
Classifier: Programming Language :: Python :: 3.9
Classifier: Programming Language :: Python :: 3.10
Classifier: Programming Language :: Python :: 3.11
Classifier: Programming Language :: Python :: Implementation :: PyPy
Classifier: License :: OSI Approved :: MIT License
Classifier: Operating System :: OS Independent
Requires-Python: >=3.8
License-File: LICENSE
Requires-Dist: twine
Requires-Dist: wheel
Requires-Dist: docker
Requires-Dist: pyyaml
Requires-Dist: python-dotenv
Requires-Dist: click
Requires-Dist: requests
Requires-Dist: beautifultable
Requires-Dist: termcolor
Requires-Dist: setuptools ==58.2.0
Provides-Extra: cli
Requires-Dist: click >=5.0 ; extra == 'cli'
